{
  "required": true,
  "minVersion": "0.8",
  "package": "com.paramada.marycum2024.mixins",
  "compatibilityLevel": "JAVA_17",
  "mixins": [
    "LivingEntityMixin",
    "inventory.EnderInventoryMixin",
    "inventory.InventoryMixin",
    "inventory.ItemMixin",
    "inventory.ItemStackMixin",
    "inventory.PlayerInventoryMixin",
    "inventory.SimpleInventoryMixin"
  ],
  "client": [
    "ClientPlayerEntityMixin",
    "InGameHudMixin",
    "ScreenMixin"
  ],
  "injectors": {
    "defaultRequire": 1
  }
}
